Metadata-Version: 2.1
Name: zdypt85_pkg
Version: 0.0.2
Summary: Super projekt
Author: ZDPYT85
Author-email: Zdpyt85 <zdpyt85@example.com>
Classifier: Programming Language :: Python :: 3
Classifier: License :: OSI Approved :: MIT License
Classifier: Operating System :: OS Independent
Requires-Python: >=3.8
